listConversions/__init__.py
listConversions/package.py
listconversions-1.1.0.dist-info/licenses/LICENSE
listconversions-1.1.0.dist-info/METADATA
listconversions-1.1.0.dist-info/WHEEL
listconversions-1.1.0.dist-info/top_level.txt
listconversions-1.1.0.dist-info/RECORD
